PyIntelliJ2Eclipse/__init__.py
PyIntelliJ2Eclipse/int_to_ecl.py
PyIntelliJ2Eclipse-0.1.dist-info/DESCRIPTION.rst
PyIntelliJ2Eclipse-0.1.dist-info/METADATA
PyIntelliJ2Eclipse-0.1.dist-info/RECORD
PyIntelliJ2Eclipse-0.1.dist-info/WHEEL
PyIntelliJ2Eclipse-0.1.dist-info/metadata.json
PyIntelliJ2Eclipse-0.1.dist-info/top_level.txt
